Architecture.md
LICENSE
MANIFEST.in
README.md
Readme.md
pyproject.toml
setup.cfg
setup.py
tests/test_align.py
tests/test_array.py
tests/test_buffer.py
tests/test_capi.py
tests/test_chunk.py
tests/test_common.py
tests/test_context_opencl.py
tests/test_hybrid_class.py
tests/test_kernel.py
tests/test_linked_array.py
tests/test_nplike_arrays.py
tests/test_ref.py
tests/test_scalars.py
tests/test_shared_memory.py
tests/test_strides.py
tests/test_string.py
tests/test_struct.py
tests/test_to_dict.py
tests/test_typeutils.py
tests/test_unionref.py
xobjects/__init__.py
xobjects/_patch_pyopencl_array.py
xobjects/_version.py
xobjects/array.py
xobjects/capi.py
xobjects/context.py
xobjects/context_cpu.py
xobjects/context_cupy.py
xobjects/context_pyopencl.py
xobjects/general.py
xobjects/hybrid_class.py
xobjects/linkedarray.py
xobjects/ref.py
xobjects/scalar.py
xobjects/specialize_source.py
xobjects/string.py
xobjects/struct.py
xobjects/test_helpers.py
xobjects/typeutils.py
xobjects/union.py
xobjects.egg-info/PKG-INFO
xobjects.egg-info/SOURCES.txt
xobjects.egg-info/dependency_links.txt
xobjects.egg-info/entry_points.txt
xobjects.egg-info/requires.txt
xobjects.egg-info/top_level.txt
xobjects/headers/atomicadd.h
xobjects/headers/common.h